{"items": [{"title": "辽宁一橡皮艇闪爆致7死1失联", "rank": 5, "url": "https://s.weibo.com/weibo?q=%E8%BE%BD%E5%AE%81%E4%B8%80%E6%A9%A1%E7%9A%AE%E8%89%87%E9%97%AA%E7%88%86%E8%87%B47%E6%AD%BB1%E5%A4%B1%E8%81%94"}, {"title": "中国夫妇印尼溺亡水下画面曝光", "rank": 11, "url": "https://s.weibo.com/weibo?q=%E4%B8%AD%E5%9B%BD%E5%A4%AB%E5%A6%87%E5%8D%B0%E5%B0%BC%E6%BA%BA%E4%BA%A1%E6%B0%B4%E4%B8%8B%E7%94%BB%E9%9D%A2%E6%9B%9D%E5%85%89"}, {"title": "快救救朱志鑫颤抖的手", "rank": 19, "url": "https://s.weibo.com/weibo?q=%E5%BF%AB%E6%95%91%E6%95%91%E6%9C%B1%E5%BF%97%E9%91%AB%E9%A2%A4%E6%8A%96%E7%9A%84%E6%89%8B"}, {"title": "我已经吹不了25度的空调了", "rank": 23, "url": "https://s.weibo.com/weibo?q=%E6%88%91%E5%B7%B2%E7%BB%8F%E5%90%B9%E4%B8%8D%E4%BA%8625%E5%BA%A6%E7%9A%84%E7%A9%BA%E8%B0%83%E4%BA%86"}, {"title": "怪不得吃斑斓糕老拉肚子", "rank": 26, "url": "https://s.weibo.com/weibo?q=%E6%80%AA%E4%B8%8D%E5%BE%97%E5%90%83%E6%96%91%E6%96%93%E7%B3%95%E8%80%81%E6%8B%89%E8%82%9A%E5%AD%90"}, {"title": "左奇函心率170", "rank": 32, "url": "https://s.weibo.com/weibo?q=%E5%B7%A6%E5%A5%87%E5%87%BD%E5%BF%83%E7%8E%87170"}, {"title": "王橹杰疑似身体不适", "rank": 40, "url": "https://s.weibo.com/weibo?q=%E7%8E%8B%E6%A9%B9%E6%9D%B0%E7%96%91%E4%BC%BC%E8%BA%AB%E4%BD%93%E4%B8%8D%E9%80%82"}, {"title": "幼童澡盆溺水姑姑忘拄拐一把捞起", "rank": 41, "url": "https://s.weibo.com/weibo?q=%E5%B9%BC%E7%AB%A5%E6%BE%A1%E7%9B%86%E6%BA%BA%E6%B0%B4%E5%A7%91%E5%A7%91%E5%BF%98%E6%8B%84%E6%8B%90%E4%B8%80%E6%8A%8A%E6%8D%9E%E8%B5%B7"}, {"title": "原来减肥迈开腿是真的有用", "rank": 50, "url": "https://s.weibo.com/weibo?q=%E5%8E%9F%E6%9D%A5%E5%87%8F%E8%82%A5%E8%BF%88%E5%BC%80%E8%85%BF%E6%98%AF%E7%9C%9F%E7%9A%84%E6%9C%89%E7%94%A8"}]}