{"items": [{"title": "河南正阳介入调查河水污染农作物", "rank": 21, "url": "https://s.weibo.com/weibo?q=%E6%B2%B3%E5%8D%97%E6%AD%A3%E9%98%B3%E4%BB%8B%E5%85%A5%E8%B0%83%E6%9F%A5%E6%B2%B3%E6%B0%B4%E6%B1%A1%E6%9F%93%E5%86%9C%E4%BD%9C%E7%89%A9"}, {"title": "中国造纸学会回应纸尿裤事件", "rank": 37, "url": "https://s.weibo.com/weibo?q=%E4%B8%AD%E5%9B%BD%E9%80%A0%E7%BA%B8%E5%AD%A6%E4%BC%9A%E5%9B%9E%E5%BA%94%E7%BA%B8%E5%B0%BF%E8%A3%A4%E4%BA%8B%E4%BB%B6"}, {"title": "纸尿裤事件检测核心信息未披露", "rank": 47, "url": "https://s.weibo.com/weibo?q=%E7%BA%B8%E5%B0%BF%E8%A3%A4%E4%BA%8B%E4%BB%B6%E6%A3%80%E6%B5%8B%E6%A0%B8%E5%BF%83%E4%BF%A1%E6%81%AF%E6%9C%AA%E6%8A%AB%E9%9C%B2"}]}