{"items": [{"title": "安妮海瑟薇怀三胎", "rank": 17, "url": "https://s.weibo.com/weibo?q=%E5%AE%89%E5%A6%AE%E6%B5%B7%E7%91%9F%E8%96%87%E6%80%80%E4%B8%89%E8%83%8E"}, {"title": "改善体态最简单的方法", "rank": 23, "url": "https://s.weibo.com/weibo?q=%E6%94%B9%E5%96%84%E4%BD%93%E6%80%81%E6%9C%80%E7%AE%80%E5%8D%95%E7%9A%84%E6%96%B9%E6%B3%95"}, {"title": "医生眼中的差睡姿和好睡姿", "rank": 30, "url": "https://s.weibo.com/weibo?q=%E5%8C%BB%E7%94%9F%E7%9C%BC%E4%B8%AD%E7%9A%84%E5%B7%AE%E7%9D%A1%E5%A7%BF%E5%92%8C%E5%A5%BD%E7%9D%A1%E5%A7%BF"}, {"title": "肌肉才是你身上最值钱的长寿资产", "rank": 28, "url": "https://s.weibo.com/weibo?q=%E8%82%8C%E8%82%89%E6%89%8D%E6%98%AF%E4%BD%A0%E8%BA%AB%E4%B8%8A%E6%9C%80%E5%80%BC%E9%92%B1%E7%9A%84%E9%95%BF%E5%AF%BF%E8%B5%84%E4%BA%A7"}, {"title": "男子手上长肉芽剪了又长疑感染HPV", "rank": 34, "url": "https://s.weibo.com/weibo?q=%E7%94%B7%E5%AD%90%E6%89%8B%E4%B8%8A%E9%95%BF%E8%82%89%E8%8A%BD%E5%89%AA%E4%BA%86%E5%8F%88%E9%95%BF%E7%96%91%E6%84%9F%E6%9F%93HPV"}, {"title": "主裁判抽筋喝下神秘液体奇迹恢复", "rank": 43, "url": "https://s.weibo.com/weibo?q=%E4%B8%BB%E8%A3%81%E5%88%A4%E6%8A%BD%E7%AD%8B%E5%96%9D%E4%B8%8B%E7%A5%9E%E7%A7%98%E6%B6%B2%E4%BD%93%E5%A5%87%E8%BF%B9%E6%81%A2%E5%A4%8D"}, {"title": "官方通报郑州一汽车用品商城起火", "rank": 45, "url": "https://s.weibo.com/weibo?q=%E5%AE%98%E6%96%B9%E9%80%9A%E6%8A%A5%E9%83%91%E5%B7%9E%E4%B8%80%E6%B1%BD%E8%BD%A6%E7%94%A8%E5%93%81%E5%95%86%E5%9F%8E%E8%B5%B7%E7%81%AB"}]}