{"items": [{"title": "七旬大爷殴打8月大婴儿致死获刑12年", "rank": 5, "url": "https://s.weibo.com/weibo?q=%E4%B8%83%E6%97%AC%E5%A4%A7%E7%88%B7%E6%AE%B4%E6%89%938%E6%9C%88%E5%A4%A7%E5%A9%B4%E5%84%BF%E8%87%B4%E6%AD%BB%E8%8E%B7%E5%88%9112%E5%B9%B4"}, {"title": "花2万摘囊肿得知根本不用摘", "rank": 23, "url": "https://s.weibo.com/weibo?q=%E8%8A%B12%E4%B8%87%E6%91%98%E5%9B%8A%E8%82%BF%E5%BE%97%E7%9F%A5%E6%A0%B9%E6%9C%AC%E4%B8%8D%E7%94%A8%E6%91%98"}, {"title": "厦门一女子检出全球从未记录新基因", "rank": 49, "url": "https://s.weibo.com/weibo?q=%E5%8E%A6%E9%97%A8%E4%B8%80%E5%A5%B3%E5%AD%90%E6%A3%80%E5%87%BA%E5%85%A8%E7%90%83%E4%BB%8E%E6%9C%AA%E8%AE%B0%E5%BD%95%E6%96%B0%E5%9F%BA%E5%9B%A0"}, {"title": "销量超十万三文鱼刺身竟只能煮熟吃", "rank": 20, "url": "https://s.weibo.com/weibo?q=%E9%94%80%E9%87%8F%E8%B6%85%E5%8D%81%E4%B8%87%E4%B8%89%E6%96%87%E9%B1%BC%E5%88%BA%E8%BA%AB%E7%AB%9F%E5%8F%AA%E8%83%BD%E7%85%AE%E7%86%9F%E5%90%83"}, {"title": "生育4孩获公司奖励16万女子发声", "rank": 33, "url": "https://s.weibo.com/weibo?q=%E7%94%9F%E8%82%B24%E5%AD%A9%E8%8E%B7%E5%85%AC%E5%8F%B8%E5%A5%96%E5%8A%B116%E4%B8%87%E5%A5%B3%E5%AD%90%E5%8F%91%E5%A3%B0"}, {"title": "兽用麻醉药被加入电子烟烟弹", "rank": 37, "url": "https://s.weibo.com/weibo?q=%E5%85%BD%E7%94%A8%E9%BA%BB%E9%86%89%E8%8D%AF%E8%A2%AB%E5%8A%A0%E5%85%A5%E7%94%B5%E5%AD%90%E7%83%9F%E7%83%9F%E5%BC%B9"}, {"title": "蚊子 进化", "rank": 42, "url": "https://s.weibo.com/weibo?q=%E8%9A%8A%E5%AD%90%20%E8%BF%9B%E5%8C%96"}]}