{"items": [{"title": "不要穿灰色裤子去健身房", "rank": 4, "url": "https://s.weibo.com/weibo?q=%E4%B8%8D%E8%A6%81%E7%A9%BF%E7%81%B0%E8%89%B2%E8%A3%A4%E5%AD%90%E5%8E%BB%E5%81%A5%E8%BA%AB%E6%88%BF"}, {"title": "今日辟谣", "rank": 7, "url": "https://s.weibo.com/weibo?q=%E4%BB%8A%E6%97%A5%E8%BE%9F%E8%B0%A3"}, {"title": "肝衰竭姐姐放弃治疗救弟痛哭不想死", "rank": 17, "url": "https://s.weibo.com/weibo?q=%E8%82%9D%E8%A1%B0%E7%AB%AD%E5%A7%90%E5%A7%90%E6%94%BE%E5%BC%83%E6%B2%BB%E7%96%97%E6%95%91%E5%BC%9F%E7%97%9B%E5%93%AD%E4%B8%8D%E6%83%B3%E6%AD%BB"}, {"title": "宝妈辅导作业被气到血管破裂致偏瘫", "rank": 19, "url": "https://s.weibo.com/weibo?q=%E5%AE%9D%E5%A6%88%E8%BE%85%E5%AF%BC%E4%BD%9C%E4%B8%9A%E8%A2%AB%E6%B0%94%E5%88%B0%E8%A1%80%E7%AE%A1%E7%A0%B4%E8%A3%82%E8%87%B4%E5%81%8F%E7%98%AB"}, {"title": "小孩姐用碘伏吹风机演示指纹可视化", "rank": 33, "url": "https://s.weibo.com/weibo?q=%E5%B0%8F%E5%AD%A9%E5%A7%90%E7%94%A8%E7%A2%98%E4%BC%8F%E5%90%B9%E9%A3%8E%E6%9C%BA%E6%BC%94%E7%A4%BA%E6%8C%87%E7%BA%B9%E5%8F%AF%E8%A7%86%E5%8C%96"}, {"title": "2米眼镜蛇藏引擎盖车主险伸手拔", "rank": 43, "url": "https://s.weibo.com/weibo?q=2%E7%B1%B3%E7%9C%BC%E9%95%9C%E8%9B%87%E8%97%8F%E5%BC%95%E6%93%8E%E7%9B%96%E8%BD%A6%E4%B8%BB%E9%99%A9%E4%BC%B8%E6%89%8B%E6%8B%94"}]}